mnectar/__init__.py
mnectar/__main__.py
mnectar/action.py
mnectar/appinit.py
mnectar/config.py
mnectar/logConfig.py
mnectar/registry.py
mnectar/setting.py
mnectar/signalcontrol.py
mnectar/vars.py
mnectar/backend/__init__.py
mnectar/backend/macos_key.py
mnectar/backend/mock.py
mnectar/backend/order.py
mnectar/backend/vlc.py
mnectar/formats/__init__.py
mnectar/formats/mrl.py
mnectar/formats/mutagen/__init__.py
mnectar/formats/mutagen/base.py
mnectar/formats/mutagen/mp3.py
mnectar/library/LarkSearchEngine.py
mnectar/library/TinydbStorage.py
mnectar/library/__init__.py
mnectar/library/abc.py
mnectar/library/column.py
mnectar/library/manager.py
mnectar/library/registry.py
mnectar/library/view.py
mnectar/plugins/__init__.py
mnectar/plugins/album_skip.py
mnectar/plugins/logic.py
mnectar/plugins/hashtag/__init__.py
mnectar/plugins/hashtag/column.py
mnectar/plugins/hashtag/hashtag.py
mnectar/plugins/hashtag/manager.py
mnectar/plugins/hashtag/manager_UI.py
mnectar/plugins/library/LibraryWatchdog.py
mnectar/plugins/library/__init__.py
mnectar/plugins/ui/__init__.py
mnectar/plugins/ui/pyqt5/__init__.py
mnectar/plugins/ui/pyqt5/console.py
mnectar/plugins/ui/pyqt5/m3u_export.py
mnectar/plugins/ui/pyqt5/order.py
mnectar/plugins/ui/pyqt5/queue.py
mnectar/ui/__init__.py
mnectar/ui/manager.py
mnectar/ui/pyqt5/ActionCreator.py
mnectar/ui/pyqt5/Dockable.py
mnectar/ui/pyqt5/LibrarySettings_UI.py
mnectar/ui/pyqt5/MainWindow.py
mnectar/ui/pyqt5/MainWindow_UI.py
mnectar/ui/pyqt5/PlaybackControl.py
mnectar/ui/pyqt5/PlaybackControl_UI.py
mnectar/ui/pyqt5/PlaybackControl_rc.py
mnectar/ui/pyqt5/PlaybackStatusCoverText_UI.py
mnectar/ui/pyqt5/PlaybackStatusText.py
mnectar/ui/pyqt5/PlaybackStatusText_UI.py
mnectar/ui/pyqt5/PlaylistDetail_UI.py
mnectar/ui/pyqt5/QPlaylistModel.py
mnectar/ui/pyqt5/QPlaylistView.py
mnectar/ui/pyqt5/__init__.py
mnectar/ui/pyqt5/action.py
mnectar/ui/pyqt5/browser.py
mnectar/ui/pyqt5/htmldelegate.py
mnectar/ui/pyqt5/pyqtsignal.py
mnectar/ui/pyqt5/roles.py
MoonNectar-0.6.0.dist-info/LICENSE.txt
MoonNectar-0.6.0.dist-info/METADATA
MoonNectar-0.6.0.dist-info/WHEEL
MoonNectar-0.6.0.dist-info/entry_points.txt
MoonNectar-0.6.0.dist-info/top_level.txt
MoonNectar-0.6.0.dist-info/RECORD
